<Properties StartupConfiguration="{05125C67-D00C-4A6C-88AD-AC1B55CFCB64}|Default">
  <MonoDevelop.Ide.Workbench ActiveDocument="NyanCat_C_Sharp/ViewController.cs">
    <Files>
      <File FileName="NyanCat_C_Sharp/ViewController.cs" Line="34" Column="1" />
      <File FileName="NyanCat_C_Sharp/AppDelegate.cs" Line="2" Column="14" />
    </Files>
    <Pads>
      <Pad Id="ProjectPad">
        <State name="__root__">
          <Node name="NyanCat_C_Sharp" expanded="True">
            <Node name="NyanCat_C_Sharp" expanded="True">
              <Node name="ViewController.cs" expanded="True" selected="True" />
            </Node>
          </Node>
        </State>
      </Pad>
    </Pads>
  </MonoDevelop.Ide.Workbench>
  <MonoDevelop.Ide.ItemProperties.NyanCat__C__Sharp PreferredExecutionTarget="Test1" />
  <MonoDevelop.Ide.DebuggingService.PinnedWatches />
  <MonoDevelop.Ide.Workspace ActiveConfiguration="Debug" />
  <MonoDevelop.Ide.DebuggingService.Breakpoints>
    <BreakpointStore />
  </MonoDevelop.Ide.DebuggingService.Breakpoints>
  <MultiItemStartupConfigurations />
</Properties>